tpath/__init__.py
tpath/_constants.py
tpath/_core.py
tpath/_size.py
tpath/_time.py
tpath/_utils.py
tpath/py.typed
tpath-0.9.0.dist-info/METADATA
tpath-0.9.0.dist-info/WHEEL
tpath-0.9.0.dist-info/licenses/LICENSE
tpath-0.9.0.dist-info/RECORD
