Metadata-Version: 2.4
Name: tpath
Version: 0.9.0
Summary: Enhanced pathlib with age and size utilities using lambdas
Project-URL: Homepage, https://github.com/hucker/tpath
Project-URL: Documentation, https://github.com/hucker/tpath#readme
Project-URL: Repository, https://github.com/hucker/tpath.git
Project-URL: Bug Tracker, https://github.com/hucker/tpath/issues
Project-URL: Changelog, https://github.com/hucker/tpath/blob/main/CHANGELOG.md
Author-email: Chuck Bass <chuck@acrocad.net>
Maintainer-email: Chuck Bass <chuck@acrocad.net>
License: MIT
License-File: LICENSE
Keywords: age,file,lambda,pathlib,size,tpath,utility
Classifier: Development Status :: 4 - Beta
Classifier: Intended Audience :: Developers
Classifier: License :: OSI Approved :: MIT License
Classifier: Operating System :: OS Independent
Classifier: Programming Language :: Python :: 3
Classifier: Programming Language :: Python :: 3.10
Classifier: Programming Language :: Python :: 3.11
Classifier: Programming Language :: Python :: 3.12
Classifier: Programming Language :: Python :: 3.13
Classifier: Programming Language :: Python :: 3.14
Classifier: Topic :: Software Development :: Libraries :: Python Modules
Classifier: Topic :: System :: Filesystems
Classifier: Topic :: Utilities
Classifier: Typing :: Typed
Requires-Python: >=3.10
Requires-Dist: frist>=0.18.0
Provides-Extra: dev
Requires-Dist: coverage>=7.0; extra == 'dev'
Requires-Dist: mypy>=1.0; extra == 'dev'
Requires-Dist: pre-commit>=3.0; extra == 'dev'
Requires-Dist: pytest-cov>=4.0; extra == 'dev'
Requires-Dist: pytest>=7.0; extra == 'dev'
Requires-Dist: ruff>=0.1.0; extra == 'dev'
Provides-Extra: lint
Requires-Dist: mypy>=1.0; extra == 'lint'
Requires-Dist: ruff>=0.1.0; extra == 'lint'
Provides-Extra: test
Requires-Dist: pytest-cov>=4.0; extra == 'test'
Requires-Dist: pytest>=7.0; extra == 'test'
